AUTHORS
ChangeLog
LICENSE
README.en.md
README.md
setup.cfg
setup.py
biban/__init__.py
biban/hello.py
biban.egg-info/PKG-INFO
biban.egg-info/SOURCES.txt
biban.egg-info/dependency_links.txt
biban.egg-info/entry_points.txt
biban.egg-info/not-zip-safe
biban.egg-info/requires.txt
biban.egg-info/top_level.txt